peruse/__init__.py
peruse/single_wf_snip_analysis.py
peruse/slang_lite_py2http_ws.py
peruse/slang_lite_ws.py
peruse/util.py
peruse/scrap/__init__.py
peruse/scrap/correlation_detection.py
peruse-0.0.13.dist-info/LICENSE
peruse-0.0.13.dist-info/METADATA
peruse-0.0.13.dist-info/WHEEL
peruse-0.0.13.dist-info/top_level.txt
peruse-0.0.13.dist-info/RECORD
