Metadata-Version: 2.1
Name: peruse
Version: 0.0.13
Summary: Explore a waveform with slang
Home-page: https://github.com/otosense/peruse
Author: OtoSense
License: apache-2.0
Platform: any
Requires-Dist: slang
Requires-Dist: hum
Requires-Dist: numpy
Requires-Dist: scikit-learn
Requires-Dist: matplotlib
Requires-Dist: soundfile
Requires-Dist: flask
Requires-Dist: flask-cors
Requires-Dist: py2api
Requires-Dist: py2http
